lakepowell/__init__.py
lakepowell/biomass_functions.py
lakepowell/catch_per_unit_effort_functions.py
lakepowell/cleaner.py
lakepowell/correlation.py
lakepowell/data.py
lakepowell/download.py
lakepowell/filter.py
lakepowell/join.py
lakepowell/mean_and_variance_functions.py
lakepowell/operations.py
lakepowell/water_data.py
lakepowell/water_min_max.py
lakepowell-0.1.10.dist-info/LICENSE.md
lakepowell-0.1.10.dist-info/METADATA
lakepowell-0.1.10.dist-info/WHEEL
lakepowell-0.1.10.dist-info/top_level.txt
lakepowell-0.1.10.dist-info/RECORD
