Metadata-Version: 2.1
Name: lakepowell
Version: 0.1.10
Summary: lake powell Python package
Home-page: https://github.com/hboekweg/fishdata.git
Author: lakepowellapi
Author-email: lakepowellapi@gmail.com
Classifier: Programming Language :: Python :: 3
Classifier: License :: OSI Approved :: MIT License
Classifier: Operating System :: OS Independent
Requires-Python: >=3.6
License-File: LICENSE.md
